steputil/__init__.py
steputil/argparser.py
steputil/info.py
steputil-0.2.16.dist-info/licenses/LICENSE
steputil-0.2.16.dist-info/METADATA
steputil-0.2.16.dist-info/WHEEL
steputil-0.2.16.dist-info/top_level.txt
steputil-0.2.16.dist-info/RECORD
