Metadata-Version: 2.4
Name: steputil
Version: 0.2.16
Summary: Utilities to simplify creation of pipeline steps
Author-email: Jan Kneissler <j@kneissler.com>
License: MIT
Project-URL: Homepage, https://github.com/k-pipe/step-util
Project-URL: Repository, https://github.com/k-pipe/step-util
Project-URL: Issues, https://github.com/k-pipe/step-util/issues
Classifier: Development Status :: 3 - Alpha
Classifier: Intended Audience :: Developers
Classifier: Programming Language :: Python :: 3
Classifier: Programming Language :: Python :: 3.8
Classifier: Programming Language :: Python :: 3.9
Classifier: Programming Language :: Python :: 3.10
Classifier: Programming Language :: Python :: 3.11
Classifier: Programming Language :: Python :: 3.12
Requires-Python: >=3.8
License-File: LICENSE
Provides-Extra: dev
Requires-Dist: pytest>=7.0; extra == "dev"
Requires-Dist: pytest-cov>=4.0; extra == "dev"
Requires-Dist: black>=23.0; extra == "dev"
Requires-Dist: flake8>=6.0; extra == "dev"
Requires-Dist: mypy>=1.0; extra == "dev"
Dynamic: license-file
